pbiblio/__init__.py
pbiblio/mbiblio.py
src/pbiblio/__init__.py
src/pbiblio/mbiblio.py
SimpleBiblio-3.0.dist-info/METADATA
SimpleBiblio-3.0.dist-info/WHEEL
SimpleBiblio-3.0.dist-info/top_level.txt
SimpleBiblio-3.0.dist-info/RECORD
