Metadata-Version: 2.1
Name: SimpleBiblio
Version: 3.0
Summary: Simple exemple de déploiement
Home-page: UNKNOWN
Author: Douchet
Author-email: TDouchet@eni.fr
License: UNKNOWN
Platform: UNKNOWN
